gousset/__init__.py
gousset/core.py
gousset-0.1.0.dist-info/METADATA
gousset-0.1.0.dist-info/WHEEL
gousset-0.1.0.dist-info/top_level.txt
gousset-0.1.0.dist-info/RECORD
